cms/__init__.py
cms/__main__.py
cms/api.py
cms/app_base.py
cms/app_registration.py
cms/apphook_pool.py
cms/appresolver.py
cms/apps.py
cms/cms_config.py
cms/cms_menus.py
cms/cms_plugins.py
cms/cms_toolbars.py
cms/cms_wizards.py
cms/constants.py
cms/context_processors.py
cms/exceptions.py
cms/menu_bases.py
cms/page_rendering.py
cms/plugin_base.py
cms/plugin_pool.py
cms/plugin_processors.py
cms/plugin_rendering.py
cms/templates.py
cms/toolbar_base.py
cms/toolbar_pool.py
cms/urls.py
cms/views.py
cms/admin/__init__.py
cms/admin/forms.py
cms/admin/pageadmin.py
cms/admin/permissionadmin.py
cms/admin/placeholderadmin.py
cms/admin/settingsadmin.py
cms/admin/static_placeholder.py
cms/admin/useradmin.py
cms/admin/utils.py
cms/cache/__init__.py
cms/cache/choices.py
cms/cache/page.py
cms/cache/permissions.py
cms/cache/placeholder.py
cms/extensions/__init__.py
cms/extensions/admin.py
cms/extensions/extension_pool.py
cms/extensions/models.py
cms/extensions/toolbar.py
cms/forms/__init__.py
cms/forms/fields.py
cms/forms/login.py
cms/forms/utils.py
cms/forms/validators.py
cms/forms/widgets.py
cms/forms/wizards.py
cms/locale/af/LC_MESSAGES/django.mo
cms/locale/af/LC_MESSAGES/django.po
cms/locale/af/LC_MESSAGES/djangojs.mo
cms/locale/af/LC_MESSAGES/djangojs.po
cms/locale/ar/LC_MESSAGES/django.mo
cms/locale/ar/LC_MESSAGES/django.po
cms/locale/ar/LC_MESSAGES/djangojs.mo
cms/locale/ar/LC_MESSAGES/djangojs.po
cms/locale/ar_SA/LC_MESSAGES/django.mo
cms/locale/ar_SA/LC_MESSAGES/django.po
cms/locale/ar_SA/LC_MESSAGES/djangojs.mo
cms/locale/ar_SA/LC_MESSAGES/djangojs.po
cms/locale/be/LC_MESSAGES/django.mo
cms/locale/be/LC_MESSAGES/django.po
cms/locale/be/LC_MESSAGES/djangojs.mo
cms/locale/be/LC_MESSAGES/djangojs.po
cms/locale/bg/LC_MESSAGES/django.mo
cms/locale/bg/LC_MESSAGES/django.po
cms/locale/bg/LC_MESSAGES/djangojs.mo
cms/locale/bg/LC_MESSAGES/djangojs.po
cms/locale/bn/LC_MESSAGES/django.mo
cms/locale/bn/LC_MESSAGES/django.po
cms/locale/bn/LC_MESSAGES/djangojs.mo
django_cms-5.0.5.dist-info/licenses/AUTHORS
django_cms-5.0.5.dist-info/licenses/LICENSE
django_cms-5.0.5.dist-info/METADATA
django_cms-5.0.5.dist-info/WHEEL
django_cms-5.0.5.dist-info/entry_points.txt
django_cms-5.0.5.dist-info/top_level.txt
django_cms-5.0.5.dist-info/RECORD
