Metadata-Version: 2.4
Name: django-cms
Version: 5.0.5
Summary: Lean enterprise content management powered by Django.
Home-page: https://www.django-cms.org/
Author: Django CMS Association and contributors
Author-email: info@django-cms.org
License: BSD-3-Clause
Project-URL: Documentation, https://docs.django-cms.org/
Project-URL: Release notes, https://docs.django-cms.org/en/latest/upgrade/index.html
Project-URL: Community, https://discord-support-channel.django-cms.org
Project-URL: Source, https://github.com/django-cms/django-cms
Classifier: Development Status :: 5 - Production/Stable
Classifier: Environment :: Web Environment
Classifier: Framework :: Django
Classifier: Intended Audience :: Developers
Classifier: License :: OSI Approved :: BSD License
Classifier: Operating System :: OS Independent
Classifier: Programming Language :: Python
Classifier: Programming Language :: Python :: 3
Classifier: Programming Language :: Python :: 3.9
Classifier: Programming Language :: Python :: 3.10
Classifier: Programming Language :: Python :: 3.11
Classifier: Programming Language :: Python :: 3.12
Classifier: Programming Language :: Python :: 3.13
Classifier: Framework :: Django
Classifier: Framework :: Django :: 4.2
Classifier: Framework :: Django :: 5.0
Classifier: Framework :: Django :: 5.1
Classifier: Framework :: Django :: 5.2
Classifier: Topic :: Internet :: WWW/HTTP
Classifier: Topic :: Internet :: WWW/HTTP :: Dynamic Content
Classifier: Topic :: Software Development
Classifier: Topic :: Software Development :: Libraries
Classifier: Topic :: Software Development :: Libraries :: Application Frameworks
Requires-Python: >=3.8
License-File: LICENSE
License-File: AUTHORS
Requires-Dist: Django>=2.2
Requires-Dist: django-classy-tags>=0.7.2
Requires-Dist: django-formtools>=2.1
Requires-Dist: django-treebeard>=4.3
Requires-Dist: django-sekizai>=0.7
Requires-Dist: djangocms-admin-style>=1.2
Requires-Dist: packaging
Requires-Dist: setuptools
Provides-Extra: argon2
Requires-Dist: argon2-cffi>=19.1.0; extra == "argon2"
Provides-Extra: bcrypt
Requires-Dist: bcrypt; extra == "bcrypt"
Dynamic: license-file
